coreason_adlc_api/__init__.py
coreason_adlc_api/app.py
coreason_adlc_api/auth/identity.py
coreason_adlc_api/auth/schemas.py
coreason_adlc_api/client.py
coreason_adlc_api/client_auth.py
coreason_adlc_api/compliance.yaml
coreason_adlc_api/config.py
coreason_adlc_api/database.py
coreason_adlc_api/db.py
coreason_adlc_api/dependencies.py
coreason_adlc_api/exceptions.py
coreason_adlc_api/main.py
coreason_adlc_api/middleware/budget.py
coreason_adlc_api/middleware/circuit_breaker.py
coreason_adlc_api/middleware/pii.py
coreason_adlc_api/middleware/proxy.py
coreason_adlc_api/middleware/telemetry.py
coreason_adlc_api/routers/auth.py
coreason_adlc_api/routers/interceptor.py
coreason_adlc_api/routers/models.py
coreason_adlc_api/routers/schemas.py
coreason_adlc_api/routers/system.py
coreason_adlc_api/routers/vault.py
coreason_adlc_api/routers/workbench.py
coreason_adlc_api/services/models.py
coreason_adlc_api/telemetry/__init__.py
coreason_adlc_api/telemetry/worker.py
coreason_adlc_api/utils.py
coreason_adlc_api/vault/crypto.py
coreason_adlc_api/vault/schemas.py
coreason_adlc_api/vault/service.py
coreason_adlc_api/workbench/locking.py
coreason_adlc_api/workbench/schemas.py
coreason_adlc_api/workbench/service.py
coreason_adlc_api-0.2.0.dist-info/METADATA
coreason_adlc_api-0.2.0.dist-info/WHEEL
coreason_adlc_api-0.2.0.dist-info/entry_points.txt
coreason_adlc_api-0.2.0.dist-info/licenses/LICENSE
coreason_adlc_api-0.2.0.dist-info/licenses/NOTICE
coreason_adlc_api-0.2.0.dist-info/RECORD
