Metadata-Version: 2.4
Name: coreason_adlc_api
Version: 0.2.0
Summary: Secure ADLC Middleware enforcing PII scrubbing, budget caps, and strict governance.
License: # The Prosperity Public License 3.0.0
License-File: LICENSE
License-File: NOTICE
Author: Gowtham A Rao
Author-email: gowtham.rao@coreason.ai
Requires-Python: >=3.12, <3.15
Classifier: License :: Other/Proprietary License
Classifier: Programming Language :: Python :: 3.12
Classifier: Programming Language :: Python :: 3.13
Classifier: Programming Language :: Python :: 3.14
Classifier: Operating System :: OS Independent
Requires-Dist: alembic (>=1.17.2,<2.0.0)
Requires-Dist: asyncpg (>=0.31.0,<0.32.0)
Requires-Dist: cryptography (>=46.0.3,<47.0.0)
Requires-Dist: email-validator (>=2.3.0,<3.0.0)
Requires-Dist: fastapi (>=0.127.0,<0.128.0)
Requires-Dist: httpx (>=0.28.1,<0.29.0)
Requires-Dist: keyring (>=24.0.0,<25.0.0)
Requires-Dist: litellm (>=1.80.11,<2.0.0)
Requires-Dist: loguru (>=0.7.2,<0.8.0)
Requires-Dist: presidio-analyzer (>=2.2.360,<3.0.0) ; python_version < "3.14"
Requires-Dist: psycopg2-binary (>=2.9.11,<3.0.0)
Requires-Dist: pydantic-settings (>=2.12.0,<3.0.0)
Requires-Dist: pyjwt[crypto] (>=2.10.1,<3.0.0)
Requires-Dist: redis (>=7.1.0,<8.0.0)
Requires-Dist: spacy (>=3.8.11,<4.0.0)
Requires-Dist: sqlalchemy (>=2.0.45,<3.0.0)
Requires-Dist: uvicorn[standard] (>=0.40.0,<0.41.0)
Project-URL: Documentation, https://github.com/CoReason-AI/coreason_adlc_api
Project-URL: Homepage, https://github.com/CoReason-AI/coreason_adlc_api
Project-URL: Repository, https://github.com/CoReason-AI/coreason_adlc_api
